<?xml version="1.0" encoding="UTF-8"?>
<!-- This file was auto-generated from WSDL -->
<!-- by the Apache Axis2 version: 1.5.2  Built on : Sep 06, 2010 (09:42:01 CEST) -->
<serviceGroup>
    <service name="Anotaciones">
        <messageReceivers>
            <messageReceiver mep="http://www.w3.org/ns/wsdl/in-out" class="es.aytos.main.server.AnotacionesMessageReceiverInOut"/>
        </messageReceivers>
        <parameter name="ServiceClass">es.aytos.main.server.AnotacionesSkeleton</parameter>
        <parameter name="useOriginalwsdl">true</parameter>
        <parameter name="modifyUserWSDLPortAddress">true</parameter>
        <operation name="recibirMensaje" mep="http://www.w3.org/ns/wsdl/in-out" namespace="http://main.aytos.es">
            <actionMapping>urn:recibirMensaje</actionMapping>
            <outputActionMapping>urn:recibirMensajeResponse</outputActionMapping>
        </operation>
        <operation name="introducirFichero" mep="http://www.w3.org/ns/wsdl/in-out" namespace="http://main.aytos.es">
            <actionMapping>urn:introducirFichero</actionMapping>
            <outputActionMapping>urn:introducirFicheroResponse</outputActionMapping>
        </operation>
    </service>
</serviceGroup>
